xgboost_label_encoding/__init__.py
xgboost_label_encoding-0.0.6.dist-info/LICENSE
xgboost_label_encoding-0.0.6.dist-info/METADATA
xgboost_label_encoding-0.0.6.dist-info/WHEEL
xgboost_label_encoding-0.0.6.dist-info/top_level.txt
xgboost_label_encoding-0.0.6.dist-info/RECORD
