Metadata-Version: 2.1
Name: xgboost_label_encoding
Version: 0.0.6
Summary: Xgboost Label Encoding
Home-page: https://github.com/maximz/xgboost-label-encoding
Author: Maxim Zaslavsky
Author-email: maxim@maximz.com
License: MIT license
Classifier: Development Status :: 2 - Pre-Alpha
Classifier: Intended Audience :: Developers
Classifier: License :: OSI Approved :: MIT License
Classifier: Natural Language :: English
Classifier: Programming Language :: Python :: 3
Classifier: Programming Language :: Python :: 3.8
Classifier: Programming Language :: Python :: 3.9
Requires-Python: >=3.8
License-File: LICENSE
Requires-Dist: scikit-learn
Requires-Dist: xgboost <2
Requires-Dist: numpy
Requires-Dist: typing-extensions
